{
  "db_name": "PostgreSQL",
  "query": "UPDATE fleet SET min_cargo_space = $1, fleet_type = $2::fleet_type, updated_at = NOW() WHERE id = $3",
  "describe": {
    "columns": [],
    "parameters": {
      "Left": [
        "Int4",
        {
          "Custom": {
            "name": "fleet_type",
            "kind": {
              "Enum": [
                "Trading",
                "Scrapping",
                "Mining",
                "Charting",
                "Construction",
                "Manuel",
                "Contract"
              ]
            }
          }
        },
        "Int4"
      ]
    },
    "nullable": []
  },
  "hash": "14e358fa878e19e51c364bd8bb5e4d44bcfae292b47eb4c81f51d682dbe719d2"
}
