{
  "db_name": "PostgreSQL",
  "query": "\n                        SELECT COUNT(*) as \"count!\"\n                        FROM reserved_funds\n                        WHERE status = $1::fund_status\n                    ",
  "describe": {
    "columns": [
      {
        "ordinal": 0,
        "name": "count!",
        "type_info": "Int8"
      }
    ],
    "parameters": {
      "Left": [
        {
          "Custom": {
            "name": "fund_status",
            "kind": {
              "Enum": [
                "RESERVED",
                "USED",
                "CANCELLED"
              ]
            }
          }
        }
      ]
    },
    "nullable": [
      null
    ]
  },
  "hash": "f0dea169bb41d10313ed4562648e67b0cf0566211a10e3b44aa4556c60b011a2"
}
