{
  "db_name": "PostgreSQL",
  "query": "\n        SELECT\n            id,\n            waypoint_symbol,\n            ship_symbol,\n            total_price,\n            \"timestamp\"\n        FROM scrap_transaction\n        WHERE ship_symbol = $1\n        ",
  "describe": {
    "columns": [
      {
        "ordinal": 0,
        "name": "id",
        "type_info": "Int8"
      },
      {
        "ordinal": 1,
        "name": "waypoint_symbol",
        "type_info": "Varchar"
      },
      {
        "ordinal": 2,
        "name": "ship_symbol",
        "type_info": "Varchar"
      },
      {
        "ordinal": 3,
        "name": "total_price",
        "type_info": "Int4"
      },
      {
        "ordinal": 4,
        "name": "timestamp",
        "type_info": "Timestamptz"
      }
    ],
    "parameters": {
      "Left": [
        "Text"
      ]
    },
    "nullable": [
      false,
      false,
      false,
      false,
      false
    ]
  },
  "hash": "8be35a358c912492ee49fb553956526da30a917ab34f1741d21eb21b5209d08d"
}
